pyverilator/__init__.py
pyverilator/__main__.py
pyverilator/pyverilator.py
pyverilator/verilatorcpp.py
PyVerilator-0.7.0.dist-info/LICENSE.txt
PyVerilator-0.7.0.dist-info/METADATA
PyVerilator-0.7.0.dist-info/WHEEL
PyVerilator-0.7.0.dist-info/top_level.txt
PyVerilator-0.7.0.dist-info/RECORD
