Metadata-Version: 1.2
Name: PyVerilator
Version: 0.7.0
Summary: Python interface to Verilator models
Home-page: https://github.com/csail-csg/pyverilator
Author: CSAIL CSG
Author-email: acwright@mit.edu, bthom@mit.edu
License: UNKNOWN
Project-URL: Bug Reports, https://github.com/csail-csg/pyverilator/issues
Project-URL: Source, https://github.com/csail-csg/pyverilator
Keywords: Verilator Wrapper Verilog
Platform: UNKNOWN
Classifier: Development Status :: 3 - Alpha
Classifier: Intended Audience :: Developers
Classifier: Topic :: Software Development :: Build Tools
Classifier: Topic :: System :: Hardware
Classifier: License :: OSI Approved :: MIT License
Classifier: Programming Language :: Python :: 3.5
Classifier: Programming Language :: Python :: 3.6
